mumin/__init__.py
mumin/article.py
mumin/data_extractor.py
mumin/dataset.py
mumin/dgl.py
mumin/embedder.py
mumin/id_updator.py
mumin/image.py
mumin/twitter.py
mumin-1.10.0.dist-info/LICENSE
mumin-1.10.0.dist-info/WHEEL
mumin-1.10.0.dist-info/METADATA
mumin-1.10.0.dist-info/RECORD
