Metadata-Version: 2.1
Name: mumin
Version: 1.10.0
Summary: Seamlessly build the MuMiN dataset.
Home-page: https://mumin-dataset.github.io/
License: MIT
Author: Dan Saattrup Nielsen
Author-email: dan.nielsen@alexandra.dk
Requires-Python: >=3.8,<3.11
Classifier: License :: OSI Approved :: MIT License
Classifier: Programming Language :: Python :: 3
Classifier: Programming Language :: Python :: 3.10
Classifier: Programming Language :: Python :: 3.8
Classifier: Programming Language :: Python :: 3.9
Requires-Dist: newspaper3k (>=0.2.8,<0.3.0)
Requires-Dist: pandas (>=1.4.3,<2.0.0)
Requires-Dist: python-dotenv (>=0.20.0,<0.21.0)
Requires-Dist: torch (>=1.12.0,<2.0.0)
Requires-Dist: tqdm (>=4.62.0,<5.0.0)
Requires-Dist: transformers (>=4.20.0,<5.0.0)
Requires-Dist: wrapt-timeout-decorator (>=1.3.12,<2.0.0)
Project-URL: Repository, https://github.com/MuMiN-dataset/mumin-build
